meowwscraping.py
meoww_scrapping_minecraft-0.0.1.dist-info/LICENSE.txt
meoww_scrapping_minecraft-0.0.1.dist-info/METADATA
meoww_scrapping_minecraft-0.0.1.dist-info/WHEEL
meoww_scrapping_minecraft-0.0.1.dist-info/top_level.txt
meoww_scrapping_minecraft-0.0.1.dist-info/RECORD
