Metadata-Version: 2.2
Name: meoww_scrapping_minecraft
Version: 0.0.1
Summary: A small package from web-scrapping https://www.minecraftcrafting.info/
Author-email: mmeow <mmeeooww@gmail.com>
License: MIT License
Classifier: Programming Language :: Python :: 3
Classifier: Operating System :: OS Independent
Requires-Python: >=3.10
License-File: LICENSE.txt
Requires-Dist: requests>=2.32.3
Requires-Dist: beautifulsoup4>=4.13.3
Requires-Dist: pandas>=2.2.3
